[
  {
    "id": 10000,
    "script": [
      {
        "urlOpenType": 0,
        "imageId": 577,
        "url": ""
      },
      {
        "urlOpenType": 2,
        "imageId": 578,
        "url": "http://www.fate-sn.com/theater/"
      },
      {
        "urlOpenType": 0,
        "imageId": 579,
        "url": ""
      }
    ]
  },
  {
    "id": 10001,
    "script": [
      {
        "urlOpenType": 0,
        "imageId": 577,
        "url": ""
      },
      {
        "urlOpenType": 2,
        "imageId": 578,
        "url": "http://www.fate-sn.com/theater/"
      },
      {
        "urlOpenType": 0,
        "imageId": 580,
        "url": ""
      }
    ]
  },
  {
    "id": 10002,
    "script": [
      {
        "urlOpenType": 0,
        "imageId": 577,
        "url": ""
      },
      {
        "urlOpenType": 2,
        "imageId": 578,
        "url": "http://www.fate-sn.com/theater/"
      },
      {
        "urlOpenType": 0,
        "imageId": 581,
        "url": ""
      }
    ]
  },
  {
    "id": 10003,
    "script": [
      {
        "urlOpenType": 0,
        "imageId": 577,
        "url": ""
      },
      {
        "urlOpenType": 2,
        "imageId": 578,
        "url": "http://www.fate-sn.com/theater/"
      },
      {
        "urlOpenType": 0,
        "imageId": 582,
        "url": ""
      }
    ]
  },
  {
    "id": 10004,
    "script": [
      {
        "urlOpenType": 0,
        "imageId": 640,
        "url": ""
      },
      {
        "urlOpenType": 2,
        "imageId": 641,
        "url": "https://arcade.fate-go.jp/locationcampaign/"
      },
      {
        "urlOpenType": 0,
        "imageId": 642,
        "url": ""
      }
    ]
  },
  {
    "id": 10005,
    "script": [
      {
        "urlOpenType": 0,
        "imageId": 655,
        "url": ""
      },
      {
        "urlOpenType": 2,
        "imageId": 641,
        "url": "https://arcade.fate-go.jp/locationcampaign/"
      },
      {
        "urlOpenType": 0,
        "imageId": 656,
        "url": ""
      }
    ]
  },
  {
    "id": 10006,
    "script": [
      {
        "urlOpenType": 0,
        "imageId": 670,
        "url": ""
      },
      {
        "urlOpenType": 2,
        "imageId": 641,
        "url": "https://arcade.fate-go.jp/locationcampaign/"
      },
      {
        "urlOpenType": 0,
        "imageId": 671,
        "url": ""
      }
    ]
  },
  {
    "id": 10007,
    "script": [
      {
        "urlOpenType": 0,
        "imageId": 676,
        "url": ""
      },
      {
        "urlOpenType": 2,
        "imageId": 677,
        "url": "http://www.fate-sn.com/theater/"
      },
      {
        "urlOpenType": 0,
        "imageId": 678,
        "url": ""
      }
    ]
  },
  {
    "id": 10008,
    "script": [
      {
        "urlOpenType": 0,
        "imageId": 676,
        "url": ""
      },
      {
        "urlOpenType": 2,
        "imageId": 677,
        "url": "http://www.fate-sn.com/theater/"
      },
      {
        "urlOpenType": 0,
        "imageId": 679,
        "url": ""
      }
    ]
  },
  {
    "id": 10009,
    "script": [
      {
        "urlOpenType": 0,
        "imageId": 676,
        "url": ""
      },
      {
        "urlOpenType": 2,
        "imageId": 677,
        "url": "http://www.fate-sn.com/theater/"
      },
      {
        "urlOpenType": 0,
        "imageId": 680,
        "url": ""
      }
    ]
  },
  {
    "id": 10010,
    "script": [
      {
        "urlOpenType": 0,
        "imageId": 676,
        "url": ""
      },
      {
        "urlOpenType": 2,
        "imageId": 677,
        "url": "http://www.fate-sn.com/theater/"
      },
      {
        "urlOpenType": 0,
        "imageId": 681,
        "url": ""
      }
    ]
  },
  {
    "id": 10011,
    "script": [
      {
        "urlOpenType": 0,
        "imageId": 726,
        "url": ""
      },
      {
        "urlOpenType": 2,
        "imageId": 727,
        "url": "https://arcade.fate-go.jp/locationcampaign/"
      },
      {
        "urlOpenType": 0,
        "imageId": 728,
        "url": ""
      }
    ]
  }
]