[
  {
    "eventUiId": 304001,
    "priority": 1,
    "idx": 1,
    "condGroup": 1,
    "condType": 46,
    "condTargetId": 3000404,
    "condNum": 1
  },
  {
    "eventUiId": 304001,
    "priority": 2,
    "idx": 1,
    "condGroup": 1,
    "condType": 46,
    "condTargetId": 3000405,
    "condNum": 1
  },
  {
    "eventUiId": 304001,
    "priority": 3,
    "idx": 1,
    "condGroup": 1,
    "condType": 46,
    "condTargetId": 3000406,
    "condNum": 3
  },
  {
    "eventUiId": 304001,
    "priority": 4,
    "idx": 1,
    "condGroup": 1,
    "condType": 1,
    "condTargetId": 3000407,
    "condNum": 0
  },
  {
    "eventUiId": 304001,
    "priority": 5,
    "idx": 1,
    "condGroup": 1,
    "condType": 46,
    "condTargetId": 3000408,
    "condNum": 1
  },
  {
    "eventUiId": 304001,
    "priority": 6,
    "idx": 1,
    "condGroup": 1,
    "condType": 46,
    "condTargetId": 3000409,
    "condNum": 1
  },
  {
    "eventUiId": 304001,
    "priority": 7,
    "idx": 1,
    "condGroup": 1,
    "condType": 1,
    "condTargetId": 3000410,
    "condNum": 0
  },
  {
    "eventUiId": 304001,
    "priority": 8,
    "idx": 1,
    "condGroup": 1,
    "condType": 46,
    "condTargetId": 3000411,
    "condNum": 1
  },
  {
    "eventUiId": 304001,
    "priority": 9,
    "idx": 1,
    "condGroup": 1,
    "condType": 46,
    "condTargetId": 3000412,
    "condNum": 1
  },
  {
    "eventUiId": 304001,
    "priority": 10,
    "idx": 1,
    "condGroup": 1,
    "condType": 46,
    "condTargetId": 3000412,
    "condNum": 3
  },
  {
    "eventUiId": 304001,
    "priority": 11,
    "idx": 1,
    "condGroup": 1,
    "condType": 46,
    "condTargetId": 3000413,
    "condNum": 2
  },
  {
    "eventUiId": 304001,
    "priority": 12,
    "idx": 1,
    "condGroup": 1,
    "condType": 46,
    "condTargetId": 3000413,
    "condNum": 3
  },
  {
    "eventUiId": 304001,
    "priority": 13,
    "idx": 1,
    "condGroup": 1,
    "condType": 46,
    "condTargetId": 3000414,
    "condNum": 1
  },
  {
    "eventUiId": 304001,
    "priority": 14,
    "idx": 1,
    "condGroup": 1,
    "condType": 46,
    "condTargetId": 3000414,
    "condNum": 2
  },
  {
    "eventUiId": 304001,
    "priority": 15,
    "idx": 1,
    "condGroup": 1,
    "condType": 46,
    "condTargetId": 3000415,
    "condNum": 2
  },
  {
    "eventUiId": 304001,
    "priority": 16,
    "idx": 1,
    "condGroup": 1,
    "condType": 46,
    "condTargetId": 3000416,
    "condNum": 2
  },
  {
    "eventUiId": 304001,
    "priority": 17,
    "idx": 1,
    "condGroup": 1,
    "condType": 46,
    "condTargetId": 3000417,
    "condNum": 1
  },
  {
    "eventUiId": 304001,
    "priority": 18,
    "idx": 1,
    "condGroup": 1,
    "condType": 46,
    "condTargetId": 3000418,
    "condNum": 1
  },
  {
    "eventUiId": 304001,
    "priority": 19,
    "idx": 1,
    "condGroup": 1,
    "condType": 46,
    "condTargetId": 3000419,
    "condNum": 1
  },
  {
    "eventUiId": 304001,
    "priority": 20,
    "idx": 1,
    "condGroup": 1,
    "condType": 46,
    "condTargetId": 3000420,
    "condNum": 4
  },
  {
    "eventUiId": 8025001,
    "priority": 1,
    "idx": 1,
    "condGroup": 1,
    "condType": 1,
    "condTargetId": 94038402,
    "condNum": 0
  },
  {
    "eventUiId": 8025401,
    "priority": 1,
    "idx": 1,
    "condGroup": 1,
    "condType": 1,
    "condTargetId": 94040102,
    "condNum": 0
  },
  {
    "eventUiId": 8026401,
    "priority": 1,
    "idx": 1,
    "condGroup": 1,
    "condType": 1,
    "condTargetId": 94043002,
    "condNum": 0
  },
  {
    "eventUiId": 8028601,
    "priority": 1,
    "idx": 1,
    "condGroup": 1,
    "condType": 1,
    "condTargetId": 94048202,
    "condNum": 0
  },
  {
    "eventUiId": 8029101,
    "priority": 1,
    "idx": 1,
    "condGroup": 1,
    "condType": 1,
    "condTargetId": 94050202,
    "condNum": 0
  },
  {
    "eventUiId": 30047701,
    "priority": 1,
    "idx": 1,
    "condGroup": 1,
    "condType": 46,
    "condTargetId": 94047746,
    "condNum": 1
  },
  {
    "eventUiId": 30047701,
    "priority": 2,
    "idx": 1,
    "condGroup": 1,
    "condType": 46,
    "condTargetId": 94047749,
    "condNum": 3
  },
  {
    "eventUiId": 30047731,
    "priority": 1,
    "idx": 1,
    "condGroup": 1,
    "condType": 46,
    "condTargetId": 94047753,
    "condNum": 1
  },
  {
    "eventUiId": 30047731,
    "priority": 2,
    "idx": 1,
    "condGroup": 1,
    "condType": 46,
    "condTargetId": 94047813,
    "condNum": 1
  },
  {
    "eventUiId": 30047731,
    "priority": 3,
    "idx": 1,
    "condGroup": 1,
    "condType": 46,
    "condTargetId": 94047815,
    "condNum": 1
  },
  {
    "eventUiId": 30047759,
    "priority": 1,
    "idx": 1,
    "condGroup": 1,
    "condType": 46,
    "condTargetId": 94047817,
    "condNum": 2
  },
  {
    "eventUiId": 30047759,
    "priority": 2,
    "idx": 1,
    "condGroup": 1,
    "condType": 46,
    "condTargetId": 94047823,
    "condNum": 1
  }
]