[
  {
    "id": 81111,
    "bannerId": 81111,
    "bannerPriority": 64,
    "terminalBannerPriority": 64,
    "noticeAt": "1758006000",
    "finishedAt": "2145888000",
    "linkType": 3,
    "linkBody": "https://fgo.bilibiligame.net/fategrandshooter2025/index.html?from=fgo",
    "deviceType": 0,
    "updatedAt": "0",
    "createdAt": "0",
    "dialogImage": "https://line3-patch-fate.bilibiligame.net/21060/RewardPic/EventBonus/2025091101/logo-456_160.png",
    "dialogText": "「Fate/Grand Shooter」官方H5小游戏正在举办中！\n攻入特异点，构筑策略，畅快射击！\n完成游戏内目标，更可获得【圣晶石X10】在内的丰厚奖励！\n\n赶快点击“前往”，游玩小游戏吧！"
  },
  {
    "id": 81130,
    "bannerId": 81130,
    "bannerPriority": 65,
    "terminalBannerPriority": 65,
    "noticeAt": "1756015200",
    "finishedAt": "1759643999",
    "linkType": 2,
    "linkBody": "SummonScene/5002937",
    "deviceType": 0,
    "updatedAt": "0",
    "createdAt": "0",
    "dialogImage": "",
    "dialogText": ""
  },
  {
    "id": 81143,
    "bannerId": 81143,
    "bannerPriority": 71,
    "terminalBannerPriority": 71,
    "noticeAt": "1758866400",
    "finishedAt": "1761803999",
    "linkType": 1,
    "linkBody": "https://line3-patch-fate.bilibiligame.net/manage/html/Notice/Game/ios/2025-09-09/activityNotice_8221_1758096883.html",
    "deviceType": 0,
    "updatedAt": "0",
    "createdAt": "0",
    "dialogImage": "",
    "dialogText": ""
  },
  {
    "id": 81144,
    "bannerId": 81144,
    "bannerPriority": 70,
    "terminalBannerPriority": 70,
    "noticeAt": "1758866400",
    "finishedAt": "1759471199",
    "linkType": 2,
    "linkBody": "SummonScene/5002950",
    "deviceType": 0,
    "updatedAt": "0",
    "createdAt": "0",
    "dialogImage": "",
    "dialogText": ""
  },
  {
    "id": 81147,
    "bannerId": 81147,
    "bannerPriority": 69,
    "terminalBannerPriority": 69,
    "noticeAt": "1759395600",
    "finishedAt": "1759989599",
    "linkType": 2,
    "linkBody": "SummonScene/5002953",
    "deviceType": 0,
    "updatedAt": "0",
    "createdAt": "0",
    "dialogImage": "",
    "dialogText": ""
  },
  {
    "id": 81148,
    "bannerId": 81148,
    "bannerPriority": 68,
    "terminalBannerPriority": 68,
    "noticeAt": "1759568400",
    "finishedAt": "1760162399",
    "linkType": 2,
    "linkBody": "SummonScene/5002954",
    "deviceType": 0,
    "updatedAt": "0",
    "createdAt": "0",
    "dialogImage": "",
    "dialogText": ""
  },
  {
    "id": 81149,
    "bannerId": 81149,
    "bannerPriority": 99,
    "terminalBannerPriority": 99,
    "noticeAt": "1759212000",
    "finishedAt": "1764482399",
    "linkType": 1,
    "linkBody": "https://line3-patch-fate.bilibiligame.net/manage/html/Notice/Game/ios/2025-09-10/activityNotice_8225_1759149140.html",
    "deviceType": 0,
    "updatedAt": "0",
    "createdAt": "0",
    "dialogImage": "",
    "dialogText": ""
  },
  {
    "id": 81150,
    "bannerId": 81150,
    "bannerPriority": 98,
    "terminalBannerPriority": 98,
    "noticeAt": "1759212000",
    "finishedAt": "1760421599",
    "linkType": 2,
    "linkBody": "SummonScene/5002957",
    "deviceType": 0,
    "updatedAt": "0",
    "createdAt": "0",
    "dialogImage": "",
    "dialogText": ""
  },
  {
    "id": 81151,
    "bannerId": 81151,
    "bannerPriority": 97,
    "terminalBannerPriority": 97,
    "noticeAt": "1759402800",
    "finishedAt": "1759489199",
    "linkType": 2,
    "linkBody": "SummonScene/5002958",
    "deviceType": 0,
    "updatedAt": "0",
    "createdAt": "0",
    "dialogImage": "",
    "dialogText": ""
  },
  {
    "id": 81152,
    "bannerId": 81152,
    "bannerPriority": 96,
    "terminalBannerPriority": 96,
    "noticeAt": "1759482000",
    "finishedAt": "1759575599",
    "linkType": 2,
    "linkBody": "SummonScene/5002959",
    "deviceType": 0,
    "updatedAt": "0",
    "createdAt": "0",
    "dialogImage": "",
    "dialogText": ""
  },
  {
    "id": 81153,
    "bannerId": 81153,
    "bannerPriority": 95,
    "terminalBannerPriority": 95,
    "noticeAt": "1759568400",
    "finishedAt": "1759661999",
    "linkType": 2,
    "linkBody": "SummonScene/5002960",
    "deviceType": 0,
    "updatedAt": "0",
    "createdAt": "0",
    "dialogImage": "",
    "dialogText": ""
  },
  {
    "id": 81154,
    "bannerId": 81154,
    "bannerPriority": 94,
    "terminalBannerPriority": 94,
    "noticeAt": "1759654800",
    "finishedAt": "1759748399",
    "linkType": 2,
    "linkBody": "SummonScene/5002961",
    "deviceType": 0,
    "updatedAt": "0",
    "createdAt": "0",
    "dialogImage": "",
    "dialogText": ""
  },
  {
    "id": 81155,
    "bannerId": 81155,
    "bannerPriority": 93,
    "terminalBannerPriority": 93,
    "noticeAt": "1759741200",
    "finishedAt": "1759834799",
    "linkType": 2,
    "linkBody": "SummonScene/5002962",
    "deviceType": 0,
    "updatedAt": "0",
    "createdAt": "0",
    "dialogImage": "",
    "dialogText": ""
  },
  {
    "id": 81156,
    "bannerId": 81156,
    "bannerPriority": 92,
    "terminalBannerPriority": 92,
    "noticeAt": "1759827600",
    "finishedAt": "1759921199",
    "linkType": 2,
    "linkBody": "SummonScene/5002963",
    "deviceType": 0,
    "updatedAt": "0",
    "createdAt": "0",
    "dialogImage": "",
    "dialogText": ""
  },
  {
    "id": 81157,
    "bannerId": 81157,
    "bannerPriority": 91,
    "terminalBannerPriority": 91,
    "noticeAt": "1759914000",
    "finishedAt": "1760007599",
    "linkType": 2,
    "linkBody": "SummonScene/5002964",
    "deviceType": 0,
    "updatedAt": "0",
    "createdAt": "0",
    "dialogImage": "",
    "dialogText": ""
  },
  {
    "id": 81158,
    "bannerId": 81158,
    "bannerPriority": 90,
    "terminalBannerPriority": 90,
    "noticeAt": "1760000400",
    "finishedAt": "1760093999",
    "linkType": 2,
    "linkBody": "SummonScene/5002965",
    "deviceType": 0,
    "updatedAt": "0",
    "createdAt": "0",
    "dialogImage": "",
    "dialogText": ""
  },
  {
    "id": 81159,
    "bannerId": 81159,
    "bannerPriority": 89,
    "terminalBannerPriority": 89,
    "noticeAt": "1760086800",
    "finishedAt": "1760180399",
    "linkType": 2,
    "linkBody": "SummonScene/5002966",
    "deviceType": 0,
    "updatedAt": "0",
    "createdAt": "0",
    "dialogImage": "",
    "dialogText": ""
  },
  {
    "id": 81160,
    "bannerId": 81160,
    "bannerPriority": 88,
    "terminalBannerPriority": 88,
    "noticeAt": "1760173200",
    "finishedAt": "1760266799",
    "linkType": 2,
    "linkBody": "SummonScene/5002967",
    "deviceType": 0,
    "updatedAt": "0",
    "createdAt": "0",
    "dialogImage": "",
    "dialogText": ""
  },
  {
    "id": 81161,
    "bannerId": 81161,
    "bannerPriority": 87,
    "terminalBannerPriority": 87,
    "noticeAt": "1760259600",
    "finishedAt": "1760353199",
    "linkType": 2,
    "linkBody": "SummonScene/5002968",
    "deviceType": 0,
    "updatedAt": "0",
    "createdAt": "0",
    "dialogImage": "",
    "dialogText": ""
  },
  {
    "id": 81162,
    "bannerId": 81162,
    "bannerPriority": 86,
    "terminalBannerPriority": 86,
    "noticeAt": "1760346000",
    "finishedAt": "1760439599",
    "linkType": 2,
    "linkBody": "SummonScene/5002969",
    "deviceType": 0,
    "updatedAt": "0",
    "createdAt": "0",
    "dialogImage": "",
    "dialogText": ""
  },
  {
    "id": 81163,
    "bannerId": 81163,
    "bannerPriority": 85,
    "terminalBannerPriority": 85,
    "noticeAt": "1760432400",
    "finishedAt": "1760525999",
    "linkType": 2,
    "linkBody": "SummonScene/5002970",
    "deviceType": 0,
    "updatedAt": "0",
    "createdAt": "0",
    "dialogImage": "",
    "dialogText": ""
  },
  {
    "id": 81164,
    "bannerId": 81164,
    "bannerPriority": 84,
    "terminalBannerPriority": 84,
    "noticeAt": "1760518800",
    "finishedAt": "1760612399",
    "linkType": 2,
    "linkBody": "SummonScene/5002971",
    "deviceType": 0,
    "updatedAt": "0",
    "createdAt": "0",
    "dialogImage": "",
    "dialogText": ""
  },
  {
    "id": 81165,
    "bannerId": 81165,
    "bannerPriority": 83,
    "terminalBannerPriority": 83,
    "noticeAt": "1760605200",
    "finishedAt": "1760698799",
    "linkType": 2,
    "linkBody": "SummonScene/5002972",
    "deviceType": 0,
    "updatedAt": "0",
    "createdAt": "0",
    "dialogImage": "",
    "dialogText": ""
  },
  {
    "id": 81166,
    "bannerId": 81166,
    "bannerPriority": 82,
    "terminalBannerPriority": 82,
    "noticeAt": "1760691600",
    "finishedAt": "1760785199",
    "linkType": 2,
    "linkBody": "SummonScene/5002973",
    "deviceType": 0,
    "updatedAt": "0",
    "createdAt": "0",
    "dialogImage": "",
    "dialogText": ""
  },
  {
    "id": 81167,
    "bannerId": 81167,
    "bannerPriority": 81,
    "terminalBannerPriority": 81,
    "noticeAt": "1760778000",
    "finishedAt": "1760871599",
    "linkType": 2,
    "linkBody": "SummonScene/5002974",
    "deviceType": 0,
    "updatedAt": "0",
    "createdAt": "0",
    "dialogImage": "",
    "dialogText": ""
  },
  {
    "id": 81168,
    "bannerId": 81168,
    "bannerPriority": 80,
    "terminalBannerPriority": 80,
    "noticeAt": "1760864400",
    "finishedAt": "1760957999",
    "linkType": 2,
    "linkBody": "SummonScene/5002975",
    "deviceType": 0,
    "updatedAt": "0",
    "createdAt": "0",
    "dialogImage": "",
    "dialogText": ""
  },
  {
    "id": 81169,
    "bannerId": 81169,
    "bannerPriority": 79,
    "terminalBannerPriority": 79,
    "noticeAt": "1760950800",
    "finishedAt": "1761044399",
    "linkType": 2,
    "linkBody": "SummonScene/5002976",
    "deviceType": 0,
    "updatedAt": "0",
    "createdAt": "0",
    "dialogImage": "",
    "dialogText": ""
  },
  {
    "id": 81170,
    "bannerId": 81170,
    "bannerPriority": 78,
    "terminalBannerPriority": 78,
    "noticeAt": "1761037200",
    "finishedAt": "1761130799",
    "linkType": 2,
    "linkBody": "SummonScene/5002977",
    "deviceType": 0,
    "updatedAt": "0",
    "createdAt": "0",
    "dialogImage": "",
    "dialogText": ""
  },
  {
    "id": 81171,
    "bannerId": 81171,
    "bannerPriority": 77,
    "terminalBannerPriority": 77,
    "noticeAt": "1761123600",
    "finishedAt": "1761217199",
    "linkType": 2,
    "linkBody": "SummonScene/5002978",
    "deviceType": 0,
    "updatedAt": "0",
    "createdAt": "0",
    "dialogImage": "",
    "dialogText": ""
  },
  {
    "id": 81172,
    "bannerId": 81172,
    "bannerPriority": 76,
    "terminalBannerPriority": 76,
    "noticeAt": "1761210000",
    "finishedAt": "1761303599",
    "linkType": 2,
    "linkBody": "SummonScene/5002979",
    "deviceType": 0,
    "updatedAt": "0",
    "createdAt": "0",
    "dialogImage": "",
    "dialogText": ""
  },
  {
    "id": 81173,
    "bannerId": 81173,
    "bannerPriority": 75,
    "terminalBannerPriority": 75,
    "noticeAt": "1761296400",
    "finishedAt": "1761389999",
    "linkType": 2,
    "linkBody": "SummonScene/5002980",
    "deviceType": 0,
    "updatedAt": "0",
    "createdAt": "0",
    "dialogImage": "",
    "dialogText": ""
  },
  {
    "id": 81174,
    "bannerId": 81174,
    "bannerPriority": 74,
    "terminalBannerPriority": 74,
    "noticeAt": "1761382800",
    "finishedAt": "1761476399",
    "linkType": 2,
    "linkBody": "SummonScene/5002981",
    "deviceType": 0,
    "updatedAt": "0",
    "createdAt": "0",
    "dialogImage": "",
    "dialogText": ""
  },
  {
    "id": 81175,
    "bannerId": 81175,
    "bannerPriority": 73,
    "terminalBannerPriority": 73,
    "noticeAt": "1761469200",
    "finishedAt": "1761562799",
    "linkType": 2,
    "linkBody": "SummonScene/5002982",
    "deviceType": 0,
    "updatedAt": "0",
    "createdAt": "0",
    "dialogImage": "",
    "dialogText": ""
  },
  {
    "id": 81176,
    "bannerId": 81176,
    "bannerPriority": 72,
    "terminalBannerPriority": 72,
    "noticeAt": "1761555600",
    "finishedAt": "1761649199",
    "linkType": 2,
    "linkBody": "SummonScene/5002983",
    "deviceType": 0,
    "updatedAt": "0",
    "createdAt": "0",
    "dialogImage": "",
    "dialogText": ""
  },
  {
    "id": 81185,
    "bannerId": 81185,
    "bannerPriority": 67,
    "terminalBannerPriority": 67,
    "noticeAt": "1758866400",
    "finishedAt": "1759471199",
    "linkType": 2,
    "linkBody": "SummonScene/5002955",
    "deviceType": 0,
    "updatedAt": "0",
    "createdAt": "0",
    "dialogImage": "",
    "dialogText": ""
  },
  {
    "id": 81186,
    "bannerId": 81186,
    "bannerPriority": 66,
    "terminalBannerPriority": 66,
    "noticeAt": "1758866400",
    "finishedAt": "1759471199",
    "linkType": 2,
    "linkBody": "SummonScene/5002956",
    "deviceType": 0,
    "updatedAt": "0",
    "createdAt": "0",
    "dialogImage": "",
    "dialogText": ""
  },
  {
    "id": 99998,
    "bannerId": 99998,
    "bannerPriority": 1,
    "terminalBannerPriority": 1,
    "noticeAt": "1742450400",
    "finishedAt": "2145888000",
    "linkType": 10,
    "linkBody": "https://game.bilibili.com/fgo/jumpLink/",
    "deviceType": 0,
    "updatedAt": "0",
    "createdAt": "0",
    "dialogImage": "",
    "dialogText": "前往【FGO简中小助手】官方微信助手，添加官方企业微信，\n\n完成绑定，随时获取游戏官方资讯，\n\n首次绑定还能获取2枚呼符的奖励！\n\n点击【前往】完成绑定吧！"
  }
]