[
  {
    "servants": [
      94053300,
      94053301,
      94053302,
      94053303
    ],
    "aiIds": [
      94052600,
      94052601,
      94052602,
      94052603,
      94052604
    ],
    "ratingBaseIds": [
      1,
      2,
      3,
      4,
      5,
      6
    ],
    "tacticalIds": [
      1,
      2,
      3,
      4,
      5,
      6
    ],
    "svtEquipIds": [
      0,
      0,
      0,
      0
    ],
    "stageId": 94052600,
    "forceId": 1,
    "groupId": 0,
    "masterName": "ミスターM",
    "masterImageId": 7101000,
    "searchDepth": 2,
    "pickValue": 1,
    "defenseArea": 3,
    "calcEllipsis": 100,
    "calcEllipsisMin": 0,
    "lowerThinkingValue": 0
  },
  {
    "servants": [
      94053304,
      94053305,
      94053306,
      94053307
    ],
    "aiIds": [
      94052605,
      94052606,
      94052607,
      94052608,
      94052609
    ],
    "ratingBaseIds": [
      1,
      2,
      3,
      4,
      5,
      6
    ],
    "tacticalIds": [
      1,
      2,
      3,
      4,
      5,
      6
    ],
    "svtEquipIds": [
      0,
      0,
      0,
      0
    ],
    "stageId": 94052601,
    "forceId": 1,
    "groupId": 0,
    "masterName": "ミスターM",
    "masterImageId": 7101000,
    "searchDepth": 2,
    "pickValue": 1,
    "defenseArea": 3,
    "calcEllipsis": 100,
    "calcEllipsisMin": 0,
    "lowerThinkingValue": 0
  },
  {
    "servants": [
      94053308,
      94053309,
      94053310,
      94053311,
      94053312
    ],
    "aiIds": [
      94052610,
      94052611,
      94052612,
      94052613,
      94052614,
      94052615
    ],
    "ratingBaseIds": [
      1,
      2,
      3,
      4,
      5,
      6
    ],
    "tacticalIds": [
      1,
      2,
      3,
      4,
      5,
      6
    ],
    "svtEquipIds": [
      0,
      0,
      0,
      0,
      0
    ],
    "stageId": 94052602,
    "forceId": 1,
    "groupId": 0,
    "masterName": "ミスターM",
    "masterImageId": 7101000,
    "searchDepth": 2,
    "pickValue": 1,
    "defenseArea": 3,
    "calcEllipsis": 100,
    "calcEllipsisMin": 0,
    "lowerThinkingValue": 0
  },
  {
    "servants": [
      94053313,
      94053314,
      94053315,
      94053316,
      94053317,
      94053318
    ],
    "aiIds": [
      94052616,
      94052617,
      94052618,
      94052619,
      94052620,
      94052621,
      94052622
    ],
    "ratingBaseIds": [
      1,
      2,
      3,
      4,
      5,
      6
    ],
    "tacticalIds": [
      1,
      2,
      3,
      4,
      5,
      6
    ],
    "svtEquipIds": [
      0,
      0,
      0,
      0,
      0,
      0
    ],
    "stageId": 94052603,
    "forceId": 1,
    "groupId": 0,
    "masterName": "ミスターM",
    "masterImageId": 7101000,
    "searchDepth": 2,
    "pickValue": 1,
    "defenseArea": 3,
    "calcEllipsis": 100,
    "calcEllipsisMin": 0,
    "lowerThinkingValue": 0
  },
  {
    "servants": [
      94053319,
      94053320,
      94053321,
      94053322,
      94053323,
      94053324
    ],
    "aiIds": [
      94052623,
      94052624,
      94052625,
      94052626,
      94052627,
      94052628,
      94052629
    ],
    "ratingBaseIds": [
      1,
      2,
      3,
      4,
      5,
      6
    ],
    "tacticalIds": [
      1,
      2,
      3,
      4,
      5,
      6
    ],
    "svtEquipIds": [
      0,
      0,
      0,
      0,
      0,
      0
    ],
    "stageId": 94052604,
    "forceId": 1,
    "groupId": 0,
    "masterName": "ミスターM",
    "masterImageId": 7101000,
    "searchDepth": 2,
    "pickValue": 1,
    "defenseArea": 3,
    "calcEllipsis": 100,
    "calcEllipsisMin": 0,
    "lowerThinkingValue": 0
  },
  {
    "servants": [
      94053325,
      94053326,
      94053327,
      94053328,
      94053329
    ],
    "aiIds": [
      94052630,
      94052631,
      94052632,
      94052633,
      94052634,
      94052635
    ],
    "ratingBaseIds": [
      1,
      2,
      3,
      4,
      5,
      6
    ],
    "tacticalIds": [
      1,
      2,
      3,
      4,
      5,
      6
    ],
    "svtEquipIds": [
      0,
      0,
      0,
      0,
      0
    ],
    "stageId": 94052605,
    "forceId": 1,
    "groupId": 0,
    "masterName": "ミスターM",
    "masterImageId": 7101000,
    "searchDepth": 2,
    "pickValue": 1,
    "defenseArea": 3,
    "calcEllipsis": 100,
    "calcEllipsisMin": 0,
    "lowerThinkingValue": 0
  },
  {
    "servants": [
      94053330,
      94053331,
      94053332,
      94053333,
      94053334,
      94053335,
      94053336
    ],
    "aiIds": [
      94052636,
      94052637,
      94052638,
      94052639,
      94052640,
      94052641,
      94052642,
      94052643
    ],
    "ratingBaseIds": [
      1,
      2,
      3,
      4,
      5,
      6
    ],
    "tacticalIds": [
      1,
      2,
      3,
      4,
      5,
      6
    ],
    "svtEquipIds": [
      0,
      0,
      0,
      0,
      0,
      0,
      0
    ],
    "stageId": 94052606,
    "forceId": 1,
    "groupId": 0,
    "masterName": "ミスターM",
    "masterImageId": 7101000,
    "searchDepth": 2,
    "pickValue": 1,
    "defenseArea": 3,
    "calcEllipsis": 100,
    "calcEllipsisMin": 0,
    "lowerThinkingValue": 0
  },
  {
    "servants": [
      94055900,
      94055901,
      94055902,
      94055903
    ],
    "aiIds": [
      94055900,
      94055901,
      94055902,
      94055903,
      94055904
    ],
    "ratingBaseIds": [
      1,
      2,
      3,
      4,
      5,
      6
    ],
    "tacticalIds": [
      1,
      2,
      3,
      4,
      5,
      6
    ],
    "svtEquipIds": [
      0,
      0,
      0,
      0
    ],
    "stageId": 94055900,
    "forceId": 1,
    "groupId": 0,
    "masterName": "カエサル",
    "masterImageId": 7101100,
    "searchDepth": 2,
    "pickValue": 1,
    "defenseArea": 4,
    "calcEllipsis": 100,
    "calcEllipsisMin": 0,
    "lowerThinkingValue": 0
  },
  {
    "servants": [
      94055904,
      94055905,
      94055906,
      94055907
    ],
    "aiIds": [
      94055905,
      94055906,
      94055907,
      94055908,
      94055909
    ],
    "ratingBaseIds": [
      1,
      2,
      3,
      4,
      5,
      6
    ],
    "tacticalIds": [
      1,
      2,
      3,
      4,
      5,
      6
    ],
    "svtEquipIds": [
      0,
      0,
      0,
      0
    ],
    "stageId": 94055901,
    "forceId": 1,
    "groupId": 0,
    "masterName": "カエサル",
    "masterImageId": 7101100,
    "searchDepth": 2,
    "pickValue": 1,
    "defenseArea": 4,
    "calcEllipsis": 100,
    "calcEllipsisMin": 0,
    "lowerThinkingValue": 0
  },
  {
    "servants": [
      94055908,
      94055909,
      94055910,
      94055911
    ],
    "aiIds": [
      94055910,
      94055911,
      94055912,
      94055913,
      94055914
    ],
    "ratingBaseIds": [
      1,
      2,
      3,
      4,
      5,
      6
    ],
    "tacticalIds": [
      1,
      2,
      3,
      4,
      5,
      6
    ],
    "svtEquipIds": [
      0,
      94055901,
      94055901,
      0
    ],
    "stageId": 94055902,
    "forceId": 1,
    "groupId": 0,
    "masterName": "カエサル",
    "masterImageId": 7101100,
    "searchDepth": 2,
    "pickValue": 1,
    "defenseArea": 4,
    "calcEllipsis": 100,
    "calcEllipsisMin": 0,
    "lowerThinkingValue": 0
  },
  {
    "servants": [
      94055912,
      94055913,
      94055914,
      94055915,
      94055916,
      94055917
    ],
    "aiIds": [
      94055915,
      94055916,
      94055917,
      94055918,
      94055919,
      94055920,
      94055921
    ],
    "ratingBaseIds": [
      1,
      2,
      3,
      4,
      5,
      6
    ],
    "tacticalIds": [
      1,
      2,
      3,
      4,
      5,
      6
    ],
    "svtEquipIds": [
      0,
      0,
      0,
      0,
      0,
      0
    ],
    "stageId": 94055903,
    "forceId": 1,
    "groupId": 0,
    "masterName": "カエサル",
    "masterImageId": 7101100,
    "searchDepth": 2,
    "pickValue": 1,
    "defenseArea": 4,
    "calcEllipsis": 100,
    "calcEllipsisMin": 0,
    "lowerThinkingValue": 0
  },
  {
    "servants": [
      94055918,
      94055919,
      94055920,
      94055921,
      94055922,
      94055923
    ],
    "aiIds": [
      94055922,
      94055923,
      94055924,
      94055925,
      94055926,
      94055927,
      94055928
    ],
    "ratingBaseIds": [
      1,
      2,
      3,
      4,
      5,
      6
    ],
    "tacticalIds": [
      1,
      2,
      3,
      4,
      5,
      6
    ],
    "svtEquipIds": [
      94055901,
      94055901,
      94055901,
      0,
      0,
      0
    ],
    "stageId": 94055904,
    "forceId": 1,
    "groupId": 0,
    "masterName": "カエサル",
    "masterImageId": 7101100,
    "searchDepth": 2,
    "pickValue": 1,
    "defenseArea": 4,
    "calcEllipsis": 100,
    "calcEllipsisMin": 0,
    "lowerThinkingValue": 0
  },
  {
    "servants": [
      94055924,
      94055925,
      94055926,
      94055927,
      94055928,
      94055929
    ],
    "aiIds": [
      94055929,
      94055930,
      94055931,
      94055932,
      94055933,
      94055934,
      94055935
    ],
    "ratingBaseIds": [
      1,
      2,
      3,
      4,
      5,
      6
    ],
    "tacticalIds": [
      1,
      2,
      3,
      4,
      5,
      6
    ],
    "svtEquipIds": [
      0,
      0,
      0,
      0,
      0,
      0
    ],
    "stageId": 94055905,
    "forceId": 1,
    "groupId": 0,
    "masterName": "カエサル",
    "masterImageId": 7101100,
    "searchDepth": 2,
    "pickValue": 1,
    "defenseArea": 4,
    "calcEllipsis": 100,
    "calcEllipsisMin": 0,
    "lowerThinkingValue": 0
  },
  {
    "servants": [
      94055930,
      94055931,
      94055932,
      94055933,
      94055934,
      94055935,
      94055936,
      94055937
    ],
    "aiIds": [
      94055936,
      94055937,
      94055938,
      94055939,
      94055940,
      94055941,
      94055942,
      94055943,
      94055944
    ],
    "ratingBaseIds": [
      1,
      2,
      3,
      4,
      5,
      6
    ],
    "tacticalIds": [
      1,
      2,
      3,
      4,
      5,
      6
    ],
    "svtEquipIds": [
      94055902,
      0,
      94055902,
      0,
      0,
      94055902,
      0,
      0
    ],
    "stageId": 94055906,
    "forceId": 1,
    "groupId": 0,
    "masterName": "カエサル",
    "masterImageId": 7101100,
    "searchDepth": 2,
    "pickValue": 1,
    "defenseArea": 4,
    "calcEllipsis": 100,
    "calcEllipsisMin": 0,
    "lowerThinkingValue": 0
  },
  {
    "servants": [
      94058801
    ],
    "aiIds": [],
    "ratingBaseIds": [],
    "tacticalIds": [],
    "svtEquipIds": [
      94058801
    ],
    "stageId": 94058801,
    "forceId": 0,
    "groupId": 0,
    "masterName": "",
    "masterImageId": 0,
    "searchDepth": 0,
    "pickValue": 0,
    "defenseArea": 0,
    "calcEllipsis": 100,
    "calcEllipsisMin": 0,
    "lowerThinkingValue": 0
  },
  {
    "servants": [
      94058801,
      94058802,
      94058803,
      94058804,
      94058805
    ],
    "aiIds": [
      94058801,
      94058802,
      94058803,
      94058804,
      94058805,
      94058806
    ],
    "ratingBaseIds": [
      1,
      2,
      3,
      4,
      5,
      6
    ],
    "tacticalIds": [
      1,
      2,
      3,
      4,
      5,
      6
    ],
    "svtEquipIds": [
      0,
      0,
      0,
      0,
      94058803
    ],
    "stageId": 94058801,
    "forceId": 1,
    "groupId": 0,
    "masterName": "マーリン",
    "masterImageId": 7101200,
    "searchDepth": 2,
    "pickValue": 1,
    "defenseArea": 4,
    "calcEllipsis": 100,
    "calcEllipsisMin": 0,
    "lowerThinkingValue": 0
  },
  {
    "servants": [
      94058802
    ],
    "aiIds": [],
    "ratingBaseIds": [],
    "tacticalIds": [],
    "svtEquipIds": [
      94058801
    ],
    "stageId": 94058802,
    "forceId": 0,
    "groupId": 0,
    "masterName": "",
    "masterImageId": 0,
    "searchDepth": 0,
    "pickValue": 0,
    "defenseArea": 0,
    "calcEllipsis": 100,
    "calcEllipsisMin": 0,
    "lowerThinkingValue": 0
  },
  {
    "servants": [
      94058811,
      94058812,
      94058813,
      94058814,
      94058815
    ],
    "aiIds": [
      94058811,
      94058812,
      94058813,
      94058814,
      94058815,
      94058816
    ],
    "ratingBaseIds": [
      1,
      2,
      3,
      4,
      5,
      6
    ],
    "tacticalIds": [
      1,
      2,
      3,
      4,
      5,
      6
    ],
    "svtEquipIds": [
      0,
      0,
      0,
      94058804,
      94058805
    ],
    "stageId": 94058802,
    "forceId": 1,
    "groupId": 0,
    "masterName": "マーリン",
    "masterImageId": 7101200,
    "searchDepth": 2,
    "pickValue": 1,
    "defenseArea": 4,
    "calcEllipsis": 100,
    "calcEllipsisMin": 0,
    "lowerThinkingValue": 0
  },
  {
    "servants": [
      94058803
    ],
    "aiIds": [],
    "ratingBaseIds": [],
    "tacticalIds": [],
    "svtEquipIds": [
      94058801
    ],
    "stageId": 94058803,
    "forceId": 0,
    "groupId": 0,
    "masterName": "",
    "masterImageId": 0,
    "searchDepth": 0,
    "pickValue": 0,
    "defenseArea": 0,
    "calcEllipsis": 100,
    "calcEllipsisMin": 0,
    "lowerThinkingValue": 0
  },
  {
    "servants": [
      94058831,
      94058832,
      94058833,
      94058834,
      94058835
    ],
    "aiIds": [
      94058821,
      94058822,
      94058823,
      94058824,
      94058825,
      94058826
    ],
    "ratingBaseIds": [
      1,
      2,
      3,
      4,
      5,
      6
    ],
    "tacticalIds": [
      1,
      2,
      3,
      4,
      5,
      6
    ],
    "svtEquipIds": [
      0,
      94058806,
      0,
      0,
      94058807
    ],
    "stageId": 94058803,
    "forceId": 1,
    "groupId": 0,
    "masterName": "マーリン",
    "masterImageId": 7101200,
    "searchDepth": 2,
    "pickValue": 1,
    "defenseArea": 4,
    "calcEllipsis": 100,
    "calcEllipsisMin": 0,
    "lowerThinkingValue": 0
  },
  {
    "servants": [
      94058804
    ],
    "aiIds": [],
    "ratingBaseIds": [],
    "tacticalIds": [],
    "svtEquipIds": [
      94058801
    ],
    "stageId": 94058804,
    "forceId": 0,
    "groupId": 0,
    "masterName": "",
    "masterImageId": 0,
    "searchDepth": 0,
    "pickValue": 0,
    "defenseArea": 0,
    "calcEllipsis": 100,
    "calcEllipsisMin": 0,
    "lowerThinkingValue": 0
  },
  {
    "servants": [
      94058841,
      94058842,
      94058843,
      94058844,
      94058845,
      94058846,
      94058847
    ],
    "aiIds": [
      94058831,
      94058832,
      94058833,
      94058834,
      94058835,
      94058836,
      94058837,
      94058838
    ],
    "ratingBaseIds": [
      1,
      2,
      3,
      4,
      5,
      6
    ],
    "tacticalIds": [
      1,
      2,
      3,
      4,
      5,
      6
    ],
    "svtEquipIds": [
      0,
      0,
      0,
      94058808,
      0,
      94058809,
      94058810
    ],
    "stageId": 94058804,
    "forceId": 1,
    "groupId": 0,
    "masterName": "マーリン",
    "masterImageId": 7101200,
    "searchDepth": 2,
    "pickValue": 1,
    "defenseArea": 3,
    "calcEllipsis": 100,
    "calcEllipsisMin": 0,
    "lowerThinkingValue": 0
  },
  {
    "servants": [
      94058805
    ],
    "aiIds": [],
    "ratingBaseIds": [],
    "tacticalIds": [],
    "svtEquipIds": [
      94058801
    ],
    "stageId": 94058805,
    "forceId": 0,
    "groupId": 0,
    "masterName": "",
    "masterImageId": 0,
    "searchDepth": 0,
    "pickValue": 0,
    "defenseArea": 0,
    "calcEllipsis": 100,
    "calcEllipsisMin": 0,
    "lowerThinkingValue": 0
  },
  {
    "servants": [
      94058851,
      94058852,
      94058853,
      94058854,
      94058855,
      94058856,
      94058857
    ],
    "aiIds": [
      94058841,
      94058842,
      94058843,
      94058844,
      94058845,
      94058846,
      94058847,
      94058848
    ],
    "ratingBaseIds": [
      1,
      2,
      3,
      4,
      5,
      6
    ],
    "tacticalIds": [
      1,
      2,
      3,
      4,
      5,
      6
    ],
    "svtEquipIds": [
      94058811,
      0,
      94058812,
      0,
      0,
      0,
      94058813
    ],
    "stageId": 94058805,
    "forceId": 1,
    "groupId": 0,
    "masterName": "マーリン",
    "masterImageId": 7101200,
    "searchDepth": 2,
    "pickValue": 1,
    "defenseArea": 2,
    "calcEllipsis": 100,
    "calcEllipsisMin": 0,
    "lowerThinkingValue": 0
  },
  {
    "servants": [
      94058806
    ],
    "aiIds": [],
    "ratingBaseIds": [],
    "tacticalIds": [],
    "svtEquipIds": [
      94058802
    ],
    "stageId": 94058806,
    "forceId": 0,
    "groupId": 0,
    "masterName": "",
    "masterImageId": 0,
    "searchDepth": 0,
    "pickValue": 0,
    "defenseArea": 0,
    "calcEllipsis": 100,
    "calcEllipsisMin": 0,
    "lowerThinkingValue": 0
  },
  {
    "servants": [
      94058861,
      94058862,
      94058863,
      94058864,
      94058865,
      94058866,
      94058867
    ],
    "aiIds": [
      94058851,
      94058852,
      94058853,
      94058854,
      94058855,
      94058856,
      94058857,
      94058858
    ],
    "ratingBaseIds": [
      1,
      2,
      3,
      4,
      5,
      6
    ],
    "tacticalIds": [
      1,
      2,
      3,
      4,
      5,
      6
    ],
    "svtEquipIds": [
      0,
      0,
      0,
      94058814,
      94058815,
      0,
      94058816
    ],
    "stageId": 94058806,
    "forceId": 1,
    "groupId": 0,
    "masterName": "マーリン",
    "masterImageId": 7101200,
    "searchDepth": 2,
    "pickValue": 1,
    "defenseArea": 4,
    "calcEllipsis": 100,
    "calcEllipsisMin": 0,
    "lowerThinkingValue": 0
  },
  {
    "servants": [
      94058807
    ],
    "aiIds": [],
    "ratingBaseIds": [],
    "tacticalIds": [],
    "svtEquipIds": [
      94058801
    ],
    "stageId": 94058807,
    "forceId": 0,
    "groupId": 0,
    "masterName": "",
    "masterImageId": 0,
    "searchDepth": 0,
    "pickValue": 0,
    "defenseArea": 0,
    "calcEllipsis": 100,
    "calcEllipsisMin": 0,
    "lowerThinkingValue": 0
  },
  {
    "servants": [
      94058871,
      94058872,
      94058873,
      94058874,
      94058875,
      94058876,
      94058877,
      94058878,
      94058879,
      94058880,
      94058881
    ],
    "aiIds": [
      94058861,
      94058862,
      94058863,
      94058864,
      94058865,
      94058866,
      94058867,
      94058868,
      94058869,
      94058870,
      94058871,
      94058872
    ],
    "ratingBaseIds": [
      1,
      2,
      3,
      4,
      5,
      6
    ],
    "tacticalIds": [
      1,
      2,
      3,
      4,
      5,
      6
    ],
    "svtEquipIds": [
      0,
      0,
      0,
      94058817,
      0,
      0,
      0,
      94058818,
      0,
      94058819,
      94058820
    ],
    "stageId": 94058807,
    "forceId": 1,
    "groupId": 0,
    "masterName": "マーリン",
    "masterImageId": 7101200,
    "searchDepth": 2,
    "pickValue": 1,
    "defenseArea": 4,
    "calcEllipsis": 100,
    "calcEllipsisMin": 0,
    "lowerThinkingValue": 0
  },
  {
    "servants": [
      94071401
    ],
    "aiIds": [],
    "ratingBaseIds": [],
    "tacticalIds": [],
    "svtEquipIds": [
      94058801
    ],
    "stageId": 94071401,
    "forceId": 0,
    "groupId": 0,
    "masterName": "",
    "masterImageId": 0,
    "searchDepth": 0,
    "pickValue": 0,
    "defenseArea": 0,
    "calcEllipsis": 100,
    "calcEllipsisMin": 0,
    "lowerThinkingValue": 0
  },
  {
    "servants": [
      94071401,
      94071402,
      94071403,
      94071404,
      94071405,
      94071406
    ],
    "aiIds": [
      94071401,
      94071402,
      94071403,
      94071404,
      94071405,
      94071406,
      94071407
    ],
    "ratingBaseIds": [
      1,
      2,
      3,
      4,
      5,
      6
    ],
    "tacticalIds": [
      1,
      2,
      3,
      4,
      5,
      6
    ],
    "svtEquipIds": [
      94071401,
      94071402,
      94071403,
      94071404,
      94071404,
      94071405
    ],
    "stageId": 94071401,
    "forceId": 1,
    "groupId": 0,
    "masterName": "ジナコ",
    "masterImageId": 7101400,
    "searchDepth": 2,
    "pickValue": 1,
    "defenseArea": 4,
    "calcEllipsis": 100,
    "calcEllipsisMin": 0,
    "lowerThinkingValue": 0
  },
  {
    "servants": [
      94071402
    ],
    "aiIds": [],
    "ratingBaseIds": [],
    "tacticalIds": [],
    "svtEquipIds": [
      94058801
    ],
    "stageId": 94071402,
    "forceId": 0,
    "groupId": 0,
    "masterName": "",
    "masterImageId": 0,
    "searchDepth": 0,
    "pickValue": 0,
    "defenseArea": 0,
    "calcEllipsis": 100,
    "calcEllipsisMin": 0,
    "lowerThinkingValue": 0
  },
  {
    "servants": [
      94071411,
      94071412,
      94071413,
      94071414,
      94071415,
      94071416,
      94071417
    ],
    "aiIds": [
      94071411,
      94071412,
      94071413,
      94071414,
      94071415,
      94071416,
      94071417,
      94071418
    ],
    "ratingBaseIds": [
      1,
      2,
      3,
      4,
      5,
      6
    ],
    "tacticalIds": [
      1,
      2,
      3,
      4,
      5,
      6
    ],
    "svtEquipIds": [
      94071406,
      94071406,
      94071406,
      94071404,
      94071404,
      94071404,
      94071407
    ],
    "stageId": 94071402,
    "forceId": 1,
    "groupId": 0,
    "masterName": "ジナコ",
    "masterImageId": 7101400,
    "searchDepth": 2,
    "pickValue": 1,
    "defenseArea": 4,
    "calcEllipsis": 100,
    "calcEllipsisMin": 0,
    "lowerThinkingValue": 0
  },
  {
    "servants": [
      94071403
    ],
    "aiIds": [],
    "ratingBaseIds": [],
    "tacticalIds": [],
    "svtEquipIds": [
      94058801
    ],
    "stageId": 94071403,
    "forceId": 0,
    "groupId": 0,
    "masterName": "",
    "masterImageId": 0,
    "searchDepth": 0,
    "pickValue": 0,
    "defenseArea": 0,
    "calcEllipsis": 100,
    "calcEllipsisMin": 0,
    "lowerThinkingValue": 0
  },
  {
    "servants": [
      94071421,
      94071422,
      94071423,
      94071424,
      94071425,
      94071426,
      94071427,
      94071428,
      94071429
    ],
    "aiIds": [
      94071421,
      94071422,
      94071423,
      94071424,
      94071425,
      94071426,
      94071427,
      94071428,
      94071429,
      94071430
    ],
    "ratingBaseIds": [
      1,
      2,
      3,
      4,
      5,
      6
    ],
    "tacticalIds": [
      1,
      2,
      3,
      4,
      5,
      6
    ],
    "svtEquipIds": [
      94071408,
      94071409,
      94071410,
      94071411,
      94071404,
      94071404,
      94071404,
      94071404,
      94071412
    ],
    "stageId": 94071403,
    "forceId": 1,
    "groupId": 0,
    "masterName": "ジナコ",
    "masterImageId": 7101400,
    "searchDepth": 2,
    "pickValue": 1,
    "defenseArea": 4,
    "calcEllipsis": 100,
    "calcEllipsisMin": 0,
    "lowerThinkingValue": 0
  },
  {
    "servants": [
      94071404
    ],
    "aiIds": [],
    "ratingBaseIds": [],
    "tacticalIds": [],
    "svtEquipIds": [
      94058801
    ],
    "stageId": 94071404,
    "forceId": 0,
    "groupId": 0,
    "masterName": "",
    "masterImageId": 0,
    "searchDepth": 0,
    "pickValue": 0,
    "defenseArea": 0,
    "calcEllipsis": 100,
    "calcEllipsisMin": 0,
    "lowerThinkingValue": 0
  },
  {
    "servants": [
      94071431,
      94071432,
      94071435,
      94071434,
      94071433,
      94071436,
      94071437
    ],
    "aiIds": [
      94071431,
      94071432,
      94071433,
      94071436,
      94071435,
      94071434,
      94071437,
      94071438
    ],
    "ratingBaseIds": [
      1,
      2,
      3,
      4,
      5,
      6
    ],
    "tacticalIds": [
      1,
      2,
      3,
      4,
      5,
      6
    ],
    "svtEquipIds": [
      94071413,
      94071414,
      94071417,
      94058815,
      94071415,
      94071418,
      94071419
    ],
    "stageId": 94071404,
    "forceId": 1,
    "groupId": 0,
    "masterName": "ＢＢ",
    "masterImageId": 7101500,
    "searchDepth": 2,
    "pickValue": 1,
    "defenseArea": 4,
    "calcEllipsis": 100,
    "calcEllipsisMin": 0,
    "lowerThinkingValue": 0
  },
  {
    "servants": [
      94071405
    ],
    "aiIds": [],
    "ratingBaseIds": [],
    "tacticalIds": [],
    "svtEquipIds": [
      94058801
    ],
    "stageId": 94071405,
    "forceId": 0,
    "groupId": 0,
    "masterName": "",
    "masterImageId": 0,
    "searchDepth": 0,
    "pickValue": 0,
    "defenseArea": 0,
    "calcEllipsis": 100,
    "calcEllipsisMin": 0,
    "lowerThinkingValue": 0
  },
  {
    "servants": [
      94071441,
      94071442,
      94071443,
      94071444,
      94071445,
      94071446,
      94071447
    ],
    "aiIds": [
      94071441,
      94071442,
      94071443,
      94071444,
      94071445,
      94071446,
      94071447,
      94071448
    ],
    "ratingBaseIds": [
      1,
      2,
      3,
      4,
      5,
      6
    ],
    "tacticalIds": [
      1,
      2,
      3,
      4,
      5,
      6
    ],
    "svtEquipIds": [
      94071420,
      94071421,
      94071422,
      94058804,
      94071424,
      94071425,
      94071426
    ],
    "stageId": 94071405,
    "forceId": 1,
    "groupId": 0,
    "masterName": "ＢＢ",
    "masterImageId": 7101500,
    "searchDepth": 2,
    "pickValue": 1,
    "defenseArea": 4,
    "calcEllipsis": 100,
    "calcEllipsisMin": 0,
    "lowerThinkingValue": 0
  },
  {
    "servants": [
      94071406
    ],
    "aiIds": [],
    "ratingBaseIds": [],
    "tacticalIds": [],
    "svtEquipIds": [
      94058801
    ],
    "stageId": 94071406,
    "forceId": 0,
    "groupId": 0,
    "masterName": "",
    "masterImageId": 0,
    "searchDepth": 0,
    "pickValue": 0,
    "defenseArea": 0,
    "calcEllipsis": 100,
    "calcEllipsisMin": 0,
    "lowerThinkingValue": 0
  },
  {
    "servants": [
      94071451,
      94071452,
      94071453,
      94071454,
      94071455,
      94071456,
      94071457
    ],
    "aiIds": [
      94071451,
      94071452,
      94071453,
      94071454,
      94071455,
      94071456,
      94071457,
      94071458
    ],
    "ratingBaseIds": [
      1,
      2,
      3,
      4,
      5,
      6
    ],
    "tacticalIds": [
      1,
      2,
      3,
      4,
      5,
      6
    ],
    "svtEquipIds": [
      94071427,
      94071428,
      94071429,
      94071430,
      94071418,
      94071425,
      94071431
    ],
    "stageId": 94071406,
    "forceId": 1,
    "groupId": 0,
    "masterName": "ＢＢ",
    "masterImageId": 7101500,
    "searchDepth": 2,
    "pickValue": 1,
    "defenseArea": 4,
    "calcEllipsis": 100,
    "calcEllipsisMin": 0,
    "lowerThinkingValue": 0
  },
  {
    "servants": [
      94071407
    ],
    "aiIds": [],
    "ratingBaseIds": [],
    "tacticalIds": [],
    "svtEquipIds": [
      94058801
    ],
    "stageId": 94071407,
    "forceId": 0,
    "groupId": 0,
    "masterName": "",
    "masterImageId": 0,
    "searchDepth": 0,
    "pickValue": 0,
    "defenseArea": 0,
    "calcEllipsis": 100,
    "calcEllipsisMin": 0,
    "lowerThinkingValue": 0
  },
  {
    "servants": [
      94071461,
      94071462,
      94071463,
      94071464,
      94071465,
      94071466,
      94071467,
      94071468,
      94071469,
      94071470,
      94071471,
      94071472
    ],
    "aiIds": [
      94058861,
      94071462,
      94071463,
      94071464,
      94071465,
      94071466,
      94071467,
      94071468,
      94071469,
      94071470,
      94071471,
      94071472,
      94071473
    ],
    "ratingBaseIds": [
      1,
      2,
      3,
      4,
      5,
      6
    ],
    "tacticalIds": [
      1,
      2,
      3,
      4,
      5,
      6
    ],
    "svtEquipIds": [
      94071432,
      94071433,
      94071434,
      94071435,
      94071436,
      94071437,
      94071427,
      94071439,
      94071440,
      94071440,
      94071440,
      94071441
    ],
    "stageId": 94071407,
    "forceId": 1,
    "groupId": 0,
    "masterName": "ＢＢ",
    "masterImageId": 7101900,
    "searchDepth": 2,
    "pickValue": 1,
    "defenseArea": 4,
    "calcEllipsis": 100,
    "calcEllipsisMin": 0,
    "lowerThinkingValue": 0
  },
  {
    "servants": [],
    "aiIds": [],
    "ratingBaseIds": [],
    "tacticalIds": [],
    "svtEquipIds": [
      94058801
    ],
    "stageId": 94071440,
    "forceId": 0,
    "groupId": 0,
    "masterName": "",
    "masterImageId": 0,
    "searchDepth": 0,
    "pickValue": 0,
    "defenseArea": 0,
    "calcEllipsis": 100,
    "calcEllipsisMin": 0,
    "lowerThinkingValue": 0
  },
  {
    "servants": [
      94071407,
      94071408,
      94071409
    ],
    "aiIds": [
      94071481,
      94071482,
      94071483,
      94071484
    ],
    "ratingBaseIds": [
      1,
      2,
      3,
      4,
      5,
      6
    ],
    "tacticalIds": [
      1,
      2,
      3,
      4,
      5,
      6
    ],
    "svtEquipIds": [
      0,
      0,
      0
    ],
    "stageId": 94071440,
    "forceId": 1,
    "groupId": 0,
    "masterName": "",
    "masterImageId": 7101600,
    "searchDepth": 2,
    "pickValue": 1,
    "defenseArea": 3,
    "calcEllipsis": 100,
    "calcEllipsisMin": 0,
    "lowerThinkingValue": 0
  }
]